wellcomeml/__init__.py
wellcomeml/__main__.py
wellcomeml/__version__.py
wellcomeml/logger.py
wellcomeml/utils.py
wellcomeml/datasets/__init__.py
wellcomeml/datasets/conll.py
wellcomeml/datasets/download.py
wellcomeml/datasets/hoc.py
wellcomeml/datasets/winer.py
wellcomeml/io/__init__.py
wellcomeml/io/io.py
wellcomeml/io/s3_policy_data.py
wellcomeml/metrics/__init__.py
wellcomeml/metrics/f1.py
wellcomeml/metrics/ner_classification_report.py
wellcomeml/ml/__init__.py
wellcomeml/ml/attention.py
wellcomeml/ml/bert_classifier.py
wellcomeml/ml/bert_semantic_equivalence.py
wellcomeml/ml/bert_semantic_equivalence_114056523216000_flymake.py
wellcomeml/ml/bert_semantic_equivalence_125624622305000_flymake.py
wellcomeml/ml/bert_semantic_equivalence_130334092677000_flymake.py
wellcomeml/ml/bert_semantic_equivalence_131145422905000_flymake.py
wellcomeml/ml/bert_semantic_equivalence_131855496752000_flymake.py
wellcomeml/ml/bert_vectorizer.py
wellcomeml/ml/bilstm.py
wellcomeml/ml/clustering.py
wellcomeml/ml/cnn.py
wellcomeml/ml/constants.py
wellcomeml/ml/doc2vec_vectorizer.py
wellcomeml/ml/frequency_vectorizer.py
wellcomeml/ml/keras_utils.py
wellcomeml/ml/keras_vectorizer.py
wellcomeml/ml/sent2vec_vectorizer.py
wellcomeml/ml/similarity_entity_linking.py
wellcomeml/ml/spacy_classifier.py
wellcomeml/ml/spacy_entity_linking.py
wellcomeml/ml/spacy_knowledge_base.py
wellcomeml/ml/spacy_ner.py
wellcomeml/ml/vectorizer.py
wellcomeml/ml/voting_classifier.py
wellcomeml/spacy/__init__.py
wellcomeml/spacy/spacy_doc_to_prodigy.py
wellcomeml/viz/__init__.py
wellcomeml/viz/colors.py
wellcomeml/viz/palettes.py
wellcomeml-2021.2.1.dist-info/LICENSE
wellcomeml-2021.2.1.dist-info/METADATA
wellcomeml-2021.2.1.dist-info/WHEEL
wellcomeml-2021.2.1.dist-info/top_level.txt
wellcomeml-2021.2.1.dist-info/RECORD
