Metadata-Version: 2.1
Name: wellcomeml
Version: 2021.2.1
Summary: Utilities for managing nlp models and for                      processing text-related data at Wellcome Data Labs
Home-page: https://github.com/wellcometrust/wellcomeml/tree/master
Author: Wellcome Trust DataLabs Team
Author-email: Grp_datalabs-datascience@Wellcomecloud.onmicrosoft.com
License: ['__license__']
Platform: UNKNOWN
Classifier: Programming Language :: Python :: 3
Classifier: Operating System :: OS Independent
Requires-Dist: numpy (==1.19.2)
Requires-Dist: pandas
Requires-Dist: boto3
Requires-Dist: scikit-learn
Requires-Dist: scipy (==1.4.1)
Requires-Dist: spacy[lookups,transformers] (==3.0.0)
Requires-Dist: umap-learn
Requires-Dist: nervaluate
Requires-Dist: twine
Requires-Dist: gensim
Requires-Dist: cython
Requires-Dist: flake8
Requires-Dist: black
Requires-Dist: tqdm
Provides-Extra: deep-learning
Requires-Dist: tensorflow (==2.4.0) ; extra == 'deep-learning'
Requires-Dist: torch ; extra == 'deep-learning'
Requires-Dist: transformers ; extra == 'deep-learning'
